deficrawler/__init__.py
deficrawler/api_calls.py
deficrawler/block.py
deficrawler/dex.py
deficrawler/lending.py
deficrawler/mappers.py
deficrawler/oracle.py
deficrawler/protocol_base.py
deficrawler/querys.py
deficrawler/transformer.py
deficrawler/utils.py
deficrawler/config/__init__.py
deficrawler/config/aave-2.json
deficrawler/config/aave-3.json
deficrawler/config/balancer-1.json
deficrawler/config/balancer-2.json
deficrawler/config/bancor-1.json
deficrawler/config/block-1.json
deficrawler/config/chainlink-1.json
deficrawler/config/compound-2.json
deficrawler/config/cream-2-arbitrum.json
deficrawler/config/cream-2-avalanche.json
deficrawler/config/cream-2-fantom.json
deficrawler/config/cream-2.json
deficrawler/config/dodoex-2.json
deficrawler/config/global.json
deficrawler/config/kashi-1.json
deficrawler/config/kyber-1.json
deficrawler/config/pancakeswap-1.json
deficrawler/config/pancakeswap-2.json
deficrawler/config/pangolin-1.json
deficrawler/config/protocol_template.json
deficrawler/config/quickswap-1.json
deficrawler/config/scream-1.json
deficrawler/config/sushiswap-1-ethereum.json
deficrawler/config/sushiswap-1.json
deficrawler/config/traderjoe-1.json
deficrawler/config/ubeswap-1.json
deficrawler/config/uniswap-2.json
deficrawler/config/uniswap-3.json
deficrawler/config/venus-1.json
deficrawler-0.4.0.dist-info/LICENSE
deficrawler-0.4.0.dist-info/METADATA
deficrawler-0.4.0.dist-info/WHEEL
deficrawler-0.4.0.dist-info/top_level.txt
deficrawler-0.4.0.dist-info/RECORD
