Metadata-Version: 2.1
Name: deficrawler
Version: 0.4.0
Summary: Python package to query DeFi data from several The Graph subgraphs
Home-page: https://github.com/keyko-io/defi-crawler-py
Author: keyko.io
Author-email: root@keyko.io
License: MIT
Keywords: finance,analysis
Platform: UNKNOWN
Classifier: Development Status :: 5 - Production/Stable
Classifier: Intended Audience :: Developers
Classifier: License :: OSI Approved :: Apache Software License
Classifier: Natural Language :: English
Classifier: Programming Language :: Python :: 3.7
Requires-Python: >=3
License-File: LICENSE
Requires-Dist: dict-digger
Requires-Dist: requests
Requires-Dist: retry
